MANIFEST.in
changelog.txt
license.txt
readme.txt
setup.py
credittom.egg-info/SOURCES.txt
credittom.egg-info/dependency_links.txt
credittom.egg-info/requires.txt
credittom.egg-info/top_level.txt
credittomodels/Bid.py
credittomodels/Match.py
credittomodels/Offer.py
credittomodels/User.py
credittomodels/__init__.py
credittomodels/creditto_models_pb2.py
credittomodels/objects_mapped.py
credittomodels/protobuf_handler.py
credittomodels/statuses.py
credittomodels/utils.py
credittomodels.egg-info/PKG-INFO
credittomodels.egg-info/SOURCES.txt
credittomodels.egg-info/dependency_links.txt
credittomodels.egg-info/requires.txt
credittomodels.egg-info/top_level.txt